LICENSE
README.md
setup.py
transformers_re.py
transformers_re.egg-info/PKG-INFO
transformers_re.egg-info/SOURCES.txt
transformers_re.egg-info/dependency_links.txt
transformers_re.egg-info/requires.txt
transformers_re.egg-info/top_level.txt