Metadata-Version: 2.1
Name: transformers-re
Version: 1.1.3
Summary: A Regular Expression constraint for Language Models of transformers. With this module, you can force the LLMs to generate following your regex. Using regex in tokens and tensors are also implemented in this project.
Home-page: https://github.com/kuangkzh/transformers-re
Author: kuangzh
Author-email: 1432245553@qq.com
License-File: LICENSE
